README.rst
setup.py
ropemode/__init__.py
ropemode/decorators.py
ropemode/dialog.py
ropemode/environment.py
ropemode/filter.py
ropemode/interface.py
ropemode/refactor.py
ropemode_py3k.egg-info/PKG-INFO
ropemode_py3k.egg-info/SOURCES.txt
ropemode_py3k.egg-info/dependency_links.txt
ropemode_py3k.egg-info/requires.txt
ropemode_py3k.egg-info/top_level.txt