Metadata-Version: 1.1
Name: ropemode-py3k
Version: 0.2
Summary: ropemode, a helper for using rope refactoring library in IDEs
Home-page: https://github.com/atilaneves/ropemode
Author: Atila Neves
Author-email: atila.neves@gmail.com
License: GNU GPL
Platform: UNKNOWN
Classifier: Development Status :: 4 - Beta
Classifier: Operating System :: OS Independent
Classifier: Environment :: X11 Applications
Classifier: Environment :: Win32 (MS Windows)
Classifier: Environment :: MacOS X
Classifier: Intended Audience :: Developers
Classifier: License :: OSI Approved :: GNU General Public License (GPL)
Classifier: Natural Language :: English
Classifier: Programming Language :: Python :: 3
Classifier: Topic :: Software Development
Requires: rope_py3k (>= 0.9.4)
